geo_rasterizer/__init__.py
geo_rasterizer/geo_rasterizer.py
geo_rasterizer/py.typed
geo_rasterizer-0.2.2.dist-info/LICENSE
geo_rasterizer-0.2.2.dist-info/METADATA
geo_rasterizer-0.2.2.dist-info/WHEEL
geo_rasterizer-0.2.2.dist-info/top_level.txt
geo_rasterizer-0.2.2.dist-info/RECORD
