Metadata-Version: 2.1
Name: geo-rasterizer
Version: 0.2.2
Summary: Package to rasterize shapes in a geodataframe to a reference geotif.
Author-email: RWS Datalab <datalab.codebase@rws.nl>
Project-URL: homepage, https://gitlab.com/rwsdatalab/public/codebase/image/geo-rasterizer
Project-URL: repository, https://gitlab.com/rwsdatalab/public/codebase/image/geo-rasterizer
Project-URL: changelog, https://gitlab.com/rwsdatalab/public/codebase/image/geo-rasterizer/blob/main/CHANGELOG.rst
Keywords: geo-rasterizer
Classifier: Development Status :: 2 - Pre-Alpha
Classifier: Intended Audience :: Developers
Classifier: Natural Language :: English
Classifier: Programming Language :: Python :: 3
Classifier: Programming Language :: Python :: 3.10
Classifier: Programming Language :: Python :: 3.11
Requires-Python: >=3.10
License-File: LICENSE
Requires-Dist: logginginitializer
Requires-Dist: geopandas
Requires-Dist: rasterio
Requires-Dist: matplotlib
Provides-Extra: dev
Requires-Dist: bandit ; extra == 'dev'
Requires-Dist: black ; extra == 'dev'
Requires-Dist: flake8 ; extra == 'dev'
Requires-Dist: flake8-bugbear ; extra == 'dev'
Requires-Dist: flake8-comprehensions ; extra == 'dev'
Requires-Dist: flake8-docstrings ; extra == 'dev'
Requires-Dist: flake8-polyfill ; extra == 'dev'
Requires-Dist: isort ; extra == 'dev'
Requires-Dist: mypy ; extra == 'dev'
Requires-Dist: pre-commit ; extra == 'dev'
Requires-Dist: pylint ; extra == 'dev'
Requires-Dist: pytest ; extra == 'dev'
Requires-Dist: pytest-cov ; extra == 'dev'
Requires-Dist: rstcheck[sphinx] ; extra == 'dev'
Requires-Dist: radon ; extra == 'dev'
Requires-Dist: safety ; extra == 'dev'
Provides-Extra: doc
Requires-Dist: pydata-sphinx-theme ; extra == 'doc'
Requires-Dist: sphinx ; extra == 'doc'
Requires-Dist: sphinx-autodoc-typehints ; extra == 'doc'
